ASUllmAPI/__init__.py
ASUllmAPI/api.py
ASUllmAPI/model_config.py
ASUllmAPI/multithreading.py
ASUllmAPI/utils.py
ASUllmAPI/web_socket.py
asullmapi-2.0.11.dist-info/licenses/LICENSE
asullmapi-2.0.11.dist-info/METADATA
asullmapi-2.0.11.dist-info/WHEEL
asullmapi-2.0.11.dist-info/top_level.txt
asullmapi-2.0.11.dist-info/RECORD
