Metadata-Version: 2.4
Name: ASUllmAPI
Version: 2.0.11
Summary: A simple python package to facilitate connection to ASU LLM API
Author-email: Stella Wenxing Liu <stellawenxingliu@gmail.com>, Varun Shourie <svarun195@gmail.com>
Project-URL: Homepage, https://github.com/ASU/aiml-ssmdv-student-support-ml-data-visualization
Project-URL: Issues, https://github.com/ASU/aiml-ssmdv-student-support-ml-data-visualization/issues
Classifier: Programming Language :: Python :: 3
Classifier: License :: OSI Approved :: MIT License
Classifier: Operating System :: OS Independent
Requires-Python: >=3.8
License-File: LICENSE
Requires-Dist: requests
Requires-Dist: tqdm
Requires-Dist: websockets
Requires-Dist: certifi
Dynamic: license-file
